artisan/__init__.py
artisan/_artifacts.py
artisan/_cbor_io.py
artisan/_context.py
artisan/_fs_index.py
artisan/_http.py
artisan/_misc_io.py
artisan/_namespaces.py
artisan/_schemas.py
artisan/_targets.py
artisan/py.typed
artisan_builder-0.3.0.dist-info/WHEEL
artisan_builder-0.3.0.dist-info/METADATA
artisan_builder-0.3.0.dist-info/RECORD
