Metadata-Version: 2.1
Name: artisan-builder
Version: 0.3.0
Summary: A build system for explainable science
License: MIT
Author: Mason McGill
Author-email: mmcgill@caltech.edu
Requires-Python: >=3.6,<4.0
Classifier: License :: OSI Approved :: MIT License
Classifier: Programming Language :: Python :: 3
Classifier: Programming Language :: Python :: 3.6
Classifier: Programming Language :: Python :: 3.7
Classifier: Programming Language :: Python :: 3.8
Provides-Extra: docs
Requires-Dist: cbor2 (>=5.2,<6.0)
Requires-Dist: contextvars (>=2.4,<3.0); python_version >= "3.6" and python_version < "3.7"
Requires-Dist: numpy (>=1.19,<2.0)
Requires-Dist: sphinx (>=3,<4); extra == "docs"
Requires-Dist: typing-extensions (>=3.7,<4.0)
